pniggli/__init__.py
pniggli/reduce_2d.py
pniggli/reduce_3d.py
pniggli/utils_2d.py
pniggli/utils_3d.py
pniggli/version.py
pniggli-0.1.3.dist-info/LICENSE
pniggli-0.1.3.dist-info/LICENSE.txt
pniggli-0.1.3.dist-info/METADATA
pniggli-0.1.3.dist-info/WHEEL
pniggli-0.1.3.dist-info/entry_points.txt
pniggli-0.1.3.dist-info/top_level.txt
pniggli-0.1.3.dist-info/RECORD
